eskrim/__init__.py
eskrim/eskrim.py
eskrim-1.0.9.dist-info/COPYING
eskrim-1.0.9.dist-info/METADATA
eskrim-1.0.9.dist-info/WHEEL
eskrim-1.0.9.dist-info/entry_points.txt
eskrim-1.0.9.dist-info/RECORD
