Metadata-Version: 2.1
Name: eskrim
Version: 1.0.9
Summary: ESKRIM: EStimate with K-mers the RIchness in a Microbiome
Home-page: https://github.com/metagenopolis/ESKRIM
License: GPL-3.0-or-later
Keywords: Metagenomics
Author: Florian Plaza Oñate
Author-email: florian.plaza-onate@inrae.fr
Requires-Python: >=3.12
Classifier: Environment :: Console
Classifier: Intended Audience :: Science/Research
Classifier: License :: OSI Approved :: GNU General Public License v3 or later (GPLv3+)
Classifier: Operating System :: OS Independent
Classifier: Programming Language :: Python :: 3
Classifier: Programming Language :: Python :: 3.12
Classifier: Topic :: Scientific/Engineering :: Bio-Informatics
Requires-Dist: pyjellyfish (>=1.3.1)
Project-URL: Repository, https://github.com/metagenopolis/ESKRIM
